methamplicons/__init__.py
methamplicons/extract_data.py
methamplicons/extract_meth.py
methamplicons/flash
methamplicons/linux_flash
methamplicons/main.py
methamplicons/plotter.py
methamplicons-0.3.4.dist-info/entry_points.txt
methamplicons-0.3.4.dist-info/LICENSE
methamplicons-0.3.4.dist-info/WHEEL
methamplicons-0.3.4.dist-info/METADATA
methamplicons-0.3.4.dist-info/RECORD
