Metadata-Version: 2.1
Name: methamplicons
Version: 0.3.4
Summary: MethAmplicons: A tool for plotting targeted bisulfite sequencing.
Home-page: https://github.com/molonc-lab/MethAmplicons2
Author: Brett Liddell, Olga Kondrashova
Author-email: brett.liddell@qimrberghofer.edu.au, olga.kondrashova@qimrberghofer.edu.au
Requires-Python: >=3.6
Classifier: Programming Language :: Python :: 3.6
Classifier: License :: OSI Approved :: MIT License
Requires-Dist: pandas ==1.1.5
Requires-Dist: numpy
Requires-Dist: pillow >=8.3.2
Requires-Dist: matplotlib >=3.3.1
Requires-Dist: seaborn >=0.11.1
